piggaga_models/__init__.py
piggaga_models/piggaga_models.py
piggaga_models-0.1.1.dist-info/METADATA
piggaga_models-0.1.1.dist-info/WHEEL
piggaga_models-0.1.1.dist-info/entry_points.txt
piggaga_models-0.1.1.dist-info/top_level.txt
piggaga_models-0.1.1.dist-info/RECORD
