Metadata-Version: 2.1
Name: piggaga_models
Version: 0.1.1
Summary: piggaga_models
Home-page: https://github.com/piggaga/piggaga
Author: 豬嘎嘎
Author-email: piggaga.company@gmail.com
Classifier: Programming Language :: Python :: 3
Classifier: License :: OSI Approved :: MIT License
Classifier: Operating System :: OS Independent
Requires-Python: >=3.6
Requires-Dist: requests
Requires-Dist: tqdm
Requires-Dist: rich
Requires-Dist: beautifulsoup4
Requires-Dist: openai
